{"code":"S222","name":"CHENNAI NORTH - 2","candidates":[{"name":"DR.KALANIDHI VEERASWAMY","status":"leading","gap":170398,"voteCount":250899,"party":"Dravida Munnetra Kazhagam"},{"name":"R. MANOHAR","status":"trailing","gap":-170398,"voteCount":80501,"party":"All India Anna Dravida Munnetra Kazhagam"},{"name":"R.C. PAUL KANAGARAJ","status":"trailing","gap":-183955,"voteCount":66944,"party":"Bharatiya Janata Party"},{"name":"AMUDINI","status":"trailing","gap":-198542,"voteCount":52357,"party":"Naam Tamilar Katchi"},{"name":"SARAH FATHIMA","status":"trailing","gap":-247735,"voteCount":3164,"party":"Independent"},{"name":"MOORTHY. V","status":"trailing","gap":-249258,"voteCount":1641,"party":"Independent"},{"name":"E. IQBAL","status":"trailing","gap":-249502,"voteCount":1397,"party":"Bahujan Samaj Party"},{"name":"SURIYAMUTHU","status":"trailing","gap":-250390,"voteCount":509,"party":"Independent"},{"name":"C. SENAPATHI","status":"trailing","gap":-250482,"voteCount":417,"party":"Independent"},{"name":"DILLI GANESH. E","status":"trailing","gap":-250491,"voteCount":408,"party":"Independent"},{"name":"M. ZION RAJ","status":"trailing","gap":-250519,"voteCount":380,"party":"Independent"},{"name":"U. VENKATESH","status":"trailing","gap":-250529,"voteCount":370,"party":"Independent"},{"name":"A. AJITHKUMAR","status":"trailing","gap":-250542,"voteCount":357,"party":"Thakkam Katchi"},{"name":"AKSHAY","status":"trailing","gap":-250584,"voteCount":315,"party":"Naadaalum Makkal Katchi"},{"name":"K.PALANIAPPAN","status":"trailing","gap":-250637,"voteCount":262,"party":"Independent"},{"name":"J. SEBASTIN","status":"trailing","gap":-250655,"voteCount":244,"party":"Socialist Unity Centre Of India (COMMUNIST)"},{"name":"R. SENTHIL KUMAR","status":"trailing","gap":-250658,"voteCount":241,"party":"Independent"},{"name":"B. BALAMURUGAN","status":"trailing","gap":-250681,"voteCount":218,"party":"Independent"},{"name":"MATHANKUMAR. G","status":"trailing","gap":-250687,"voteCount":212,"party":"Independent"},{"name":"M. KOLANJI","status":"trailing","gap":-250691,"voteCount":208,"party":"Independent"},{"name":"P. JAYASELAN","status":"trailing","gap":-250704,"voteCount":195,"party":"Independent"},{"name":"P. UMADEVI","status":"trailing","gap":-250713,"voteCount":186,"party":"Independent"},{"name":"K.C.JAYAPRAKASH","status":"trailing","gap":-250719,"voteCount":180,"party":"Independent"},{"name":"B. ZAKIR HUSSAIN","status":"trailing","gap":-250721,"voteCount":178,"party":"Independent"},{"name":"T. MANOHARAN","status":"trailing","gap":-250740,"voteCount":159,"party":"Independent"},{"name":"C. SRIDHAR","status":"trailing","gap":-250744,"voteCount":155,"party":"Independent"},{"name":"T. KAVIYARASU","status":"trailing","gap":-250765,"voteCount":134,"party":"Independent"},{"name":"D. SRINIVASAN","status":"trailing","gap":-250769,"voteCount":130,"party":"Independent"},{"name":"K. SAMPATH","status":"trailing","gap":-250774,"voteCount":125,"party":"Independent"},{"name":"S. RAVIKUMAR","status":"trailing","gap":-250781,"voteCount":118,"party":"Republican Party of India  (Sivaraj)"},{"name":"SATHISH. B","status":"trailing","gap":-250784,"voteCount":115,"party":"Independent"},{"name":"R.VINAYAGAMOORTHY","status":"trailing","gap":-250785,"voteCount":114,"party":"Independent"},{"name":"D. KABILAN","status":"trailing","gap":-250800,"voteCount":99,"party":"Independent"},{"name":"P. MARIMUTHU","status":"trailing","gap":-250813,"voteCount":86,"party":"Independent"},{"name":"V.MADHAN MOHAN","status":"trailing","gap":-250818,"voteCount":81,"party":"Independent"},{"name":"NOTA","status":null,"gap":0,"voteCount":7236,"party":"None of the Above"}]}